{"4708118":["ability","arc"],"5190448":["shotgun"],"5190449":[],"5190450":["power weapon","rocket launcher"],"5190451":["auto rifle"],"5190452":["hand cannon"],"5190453":["crucible","finisher"],"5190454":["scout rifle"],"5190455":["crucible","power weapon","sword"],"13409814":["auto rifle"],"28251664":["cosmodrome","super"],"28251665":["cosmodrome"],"28251666":["cosmodrome","melee"],"28251667":["cosmodrome","grenade"],"28251668":["cosmodrome","fallen"],"28251669":["cosmodrome","precision"],"28251670":["cosmodrome"],"28251671":["cosmodrome","hive"],"28251678":["cosmodrome","power weapon"],"28251679":["cosmodrome","kinetic","kinetic weapon"],"30972315":["solar"],"31218063":["hand cannon"],"42252934":["ability"],"45262603":[],"47910874":["crucible","grenade"],"58287472":["precision"],"62194641":["crucible"],"104252528":[],"104252529":["precision"],"104252531":["finisher","melee"],"104252532":[],"104252533":[],"104252534":[],"104252535":[],"125824834":["arc","crucible"],"127300168":["crucible"],"128980839":[],"130487539":["grenade launcher"],"146278979":["arc"],"147797594":["edz"],"167220051":[],"171761468":["crucible","super"],"171866827":["raid"],"179306417":["power weapon","rocket launcher"],"204755896":["precision"],"204755897":["fusion rifle"],"204755898":["auto rifle"],"204755899":["submachine gun"],"204755900":["multikill","precision"],"204755901":["hand cannon"],"204755902":["bow"],"211068288":["solar"],"213341263":["crucible"],"225464052":["arc"],"232774974":["lost sector","void"],"232774975":["lost sector","solar"],"242688673":["shotgun","submachine gun"],"242688675":["grenade launcher","power weapon","rocket launcher","sniper rifle"],"242688677":["ability","power weapon"],"242688678":["multikill","orbs"],"242688679":["power weapon","solar","void"],"249993066":["multikill","submachine gun"],"249993067":["bow","precision","scout rifle"],"285109796":["finisher","solar"],"285109798":["precision","void"],"285109799":["crucible","iron banner","multikill","solar","void"],"286561523":["europa","trace rifle"],"299576120":["grenade launcher","multikill"],"299576121":["super"],"299576122":["grenade"],"299576123":["kinetic","kinetic weapon","melee"],"299576126":["hand cannon","multikill","precision"],"299576127":["arc","multikill","power weapon","sword"],"303384168":["shotgun"],"304697572":["shotgun"],"310094086":["pulse rifle"],"316370328":["solar"],"316370329":["orbs"],"316370330":["multikill"],"316370331":["melee"],"316370334":["bow"],"320802878":["gambit"],"320802879":[],"341098154":["trace rifle"],"346100626":["crucible"],"346263927":[],"351522029":["cosmodrome","public event"],"351522030":["cosmodrome","patrol"],"351522031":["cosmodrome","energy weapon"],"365221598":["bow"],"379746735":[],"382847904":["edz","finisher"],"382847905":[],"382847906":["bow","edz","sniper rifle"],"382847907":["power weapon"],"382847908":["cosmodrome"],"382847909":["edz"],"382847910":["precision"],"382847911":[],"382847914":["cabal"],"382847915":["taken"],"391818767":[],"399175734":["champion","lost sector"],"399175735":["lost sector"],"399625488":["solar"],"399625489":[],"399625490":["arc"],"399625491":["void"],"399625492":["ability","solar"],"399625493":["ability","arc"],"399625494":["ability","edz"],"399625495":["ability","void"],"399625500":["grenade launcher"],"399625501":[],"400298576":["finisher"],"400298584":["solar"],"400298585":["arc"],"400298586":["void"],"400298587":["grenade"],"400298588":["melee"],"400298589":["orbs"],"400298591":["ability","arc"],"430119471":["gambit","solar"],"437043264":["orbs"],"437043265":["bow","precision","scout rifle"],"437043266":[],"437043267":["auto rifle","multikill","submachine gun"],"437043268":[],"437043269":["bow"],"437043270":["ability"],"437043271":[],"437043274":["power weapon","rocket launcher"],"437043275":["scout rifle","submachine gun"],"438027978":["grenade","nessus"],"443167571":[],"447265979":["arc","gambit"],"455233900":[],"459676116":["gambit"],"463685197":["europa","shotgun"],"484780086":[],"487022728":["nessus","precision"],"489973662":["multikill","trace rifle"],"501758776":["fallen","strikes"],"511160301":[],"515493511":["crucible"],"527367198":["ability","gambit"],"542328999":[],"550008052":["sniper rifle"],"552709552":["gambit"],"552709553":["gambit"],"552709554":["gambit"],"552709555":["gambit"],"552709556":["gambit"],"552709557":["gambit"],"552709558":["ability","arc","gambit"],"552709559":["ability","gambit","solar"],"552709560":["ability","gambit","void"],"552709561":["gambit"],"553469003":["fallen","nessus"],"596183121":["bake"],"609421552":["lost sector","multikill"],"609421553":["lost sector"],"609421554":["patrol"],"609421555":[],"609421556":["public event","void"],"609421557":["arc","public event"],"609421558":["public event","solar"],"609421566":[],"609421567":["ability","lost sector","super"],"617772226":["crucible"],"631065801":["moon"],"672179719":["crucible"],"679437494":["europa","scout rifle"],"685751430":["edz","super"],"687204872":["bake"],"692493341":["submachine gun"],"709535744":["energy weapon"],"709535745":["kinetic"],"709535746":["auto rifle","multikill"],"709535747":["moon"],"709535748":["multikill"],"709535749":["multikill","submachine gun"],"709535750":["hand cannon","multikill"],"709535751":["power weapon"],"711076968":[],"711490543":["submachine gun"],"712137159":["submachine gun"],"733876604":["crucible"],"738267610":["taken"],"738267611":["solar"],"743499071":["precision"],"756469295":["nessus","solar"],"763567879":["grenade launcher"],"768824550":["europa","machine gun"],"770484014":["bow","precision","scout rifle"],"770484015":["multikill","power weapon","submachine gun"],"793232654":["public event"],"793232655":["arc","solar","void"],"836380479":["scout rifle"],"840802057":["edz","grenade"],"847805104":["shotgun"],"848944256":["precision"],"848944257":["finisher"],"848944258":[],"848944259":[],"848944260":[],"848944261":["kinetic"],"848944262":["arc"],"848944263":["void"],"852248609":["gambit"],"857633000":["hive","strikes"],"871673916":[],"874160405":["scout rifle"],"877925542":["europa","kinetic","kinetic weapon"],"897978137":["crucible","solar"],"901575776":["precision","vex"],"901575777":["vex"],"901575778":[],"901575779":["void"],"901575780":["arc"],"901575781":["solar"],"901575782":["precision"],"901575783":[],"901575790":["arc","vex"],"901575791":["solar","vex"],"903424492":["grenade"],"915363915":["gambit","void"],"956734255":["europa","pulse rifle"],"973983247":["dreaming city","lost sector"],"973983256":["dreaming city","lost sector"],"982316555":["bake"],"985646251":["crucible"],"1001399024":["dreaming city","public event"],"1008565805":["fusion rifle","multikill"],"1019699039":["grenade launcher","multikill"],"1025057518":["lost sector","moon"],"1028832205":["crucible"],"1041451527":["nessus","public event"],"1052256142":["crucible","kinetic","kinetic weapon"],"1055369100":["europa","solar"],"1058022683":["scout rifle"],"1073165367":[],"1079374388":["ability","void"],"1083494845":["kinetic","kinetic weapon"],"1087144252":["precision"],"1087144253":["multikill","nessus"],"1087144254":[],"1104345304":["multikill","nessus","super"],"1108235197":["arc","grenade"],"1108235198":["grenade","void"],"1108235199":["crucible","grenade","solar"],"1113031720":["auto rifle"],"1115575054":["ability"],"1117014939":[],"1123124244":[],"1125012752":["solar","super"],"1125012753":["super","void"],"1125012754":["edz"],"1125012755":[],"1125012756":["melee","solar"],"1125012757":["melee","void"],"1125012758":["arc","super"],"1125012759":["super"],"1125012762":["arc","melee"],"1125012763":["melee"],"1131956134":["europa","lost sector","machine gun"],"1131956135":["lost sector","precision","sniper rifle"],"1131956136":["gambit","lost sector","shotgun"],"1131956137":["lost sector","moon","submachine gun"],"1131956138":["bow","europa","lost sector","precision"],"1131956139":["gambit","lost sector","precision","sidearm"],"1131956140":["europa","hand cannon","lost sector","precision"],"1131956141":["auto rifle","europa","lost sector"],"1131956142":["lost sector","precision","pulse rifle"],"1131956143":["gambit","lost sector","precision","scout rifle"],"1136139768":["multikill"],"1136139769":["multikill","shotgun"],"1136139770":["multikill","pulse rifle"],"1136139771":["auto rifle","multikill"],"1136139774":["multikill","sniper rifle"],"1136139775":["hand cannon","multikill"],"1141790336":["grenade launcher"],"1141790337":["auto rifle","edz"],"1141790338":["edz","scout rifle"],"1141790339":["edz","grenade launcher"],"1141790340":["bow","edz"],"1141790341":[],"1141790342":["fusion rifle"],"1141790343":["power weapon","sword"],"1141790348":[],"1141790349":["edz","precision"],"1147672297":[],"1148638263":["solar"],"1151912629":["champion"],"1161773002":["crucible"],"1161773003":["gambit"],"1164306016":["scorn","solar"],"1164306017":["precision","scorn"],"1164306024":["hive"],"1164306026":["hive","solar"],"1164306027":["hive","precision"],"1164306028":["hive","void"],"1164306029":["arc","hive"],"1164306030":["scorn"],"1164306031":["hive"],"1182220675":["precision","scout rifle"],"1183240368":["moon"],"1183240369":["lost sector","moon","solar"],"1190558120":["arc","europa","fallen","moon"],"1190558122":["europa","fallen","void"],"1190558123":["europa","fallen","solar"],"1190558124":["europa","fallen","finisher","gambit"],"1190558125":["europa","fallen","precision"],"1190558127":["europa","fallen"],"1201354655":["gambit","solar"],"1202425489":["edz","orbs"],"1225647738":["dreaming city","lost sector"],"1244249306":["arc"],"1244906310":["void"],"1249076770":[],"1258056755":["submachine gun"],"1264945960":["moon"],"1272199270":["bow","precision"],"1288676952":["multikill","nessus","power weapon"],"1297871573":["edz","lost sector"],"1315013095":["void"],"1319723906":[],"1326233664":["grenade launcher","power weapon","rocket launcher"],"1326233665":["auto rifle","machine gun","pulse rifle"],"1326233666":["scorn"],"1326233667":["hive"],"1326233668":["multikill","scorn"],"1326233669":["hive","multikill"],"1326233670":["orbs"],"1326233678":["public event"],"1326233679":[],"1329813266":["cabal","nessus"],"1355586781":["power weapon","sword"],"1381806136":["nightfall"],"1391363409":[],"1403685364":["multikill"],"1403685365":[],"1403685367":[],"1405646104":["precision","sniper rifle"],"1405651514":["crucible","super"],"1407750585":["vex"],"1409078654":["nessus","void"],"1428130848":["bake"],"1428740103":["super"],"1429228592":["europa","lost sector","public event"],"1429228593":["europa","precision"],"1429228594":["europa","precision"],"1429228595":["europa","precision"],"1432499272":["arc","nessus"],"1439620178":["precision","pulse rifle"],"1441461394":["dreaming city","raid"],"1445156671":["finisher","gambit"],"1449991373":["ability"],"1453527970":["hand cannon"],"1455474223":[],"1456981581":["bake"],"1467183958":["europa"],"1467889597":["power weapon","rocket launcher"],"1474444709":["bake"],"1475436128":["orbs"],"1475436129":[],"1475436130":[],"1475436131":[],"1475436132":["pulse rifle"],"1475436133":["trace rifle"],"1475436134":["hand cannon"],"1475436135":["power weapon","sword"],"1475436138":["shotgun"],"1475436139":["grenade launcher"],"1477932524":["nightfall"],"1477932525":["nightfall"],"1477932526":["nightfall"],"1477932527":["nightfall"],"1486065664":["crucible"],"1505040824":["champion","champions","nightfall","strikes"],"1505040825":["nightfall","strikes"],"1505040826":["void"],"1505040827":["arc"],"1505040830":["solar"],"1505040831":["nightfall","strikes"],"1505100518":["crucible"],"1525024290":[],"1559535719":["crucible"],"1561597496":["auto rifle"],"1606160568":["europa","vex"],"1606160570":["europa","precision","vex"],"1606160571":["europa","finisher","vex"],"1606160572":["europa","solar","vex"],"1606160573":["europa","moon","vex","void"],"1606160575":["arc","europa","vex"],"1647137072":["kinetic","kinetic weapon"],"1647137073":["energy weapon","gambit"],"1647137080":[],"1647137081":[],"1647137082":[],"1647137083":["dreaming city","public event"],"1647137084":["dreaming city","lost sector"],"1647137085":["vex"],"1647137086":["dreaming city","taken"],"1647137087":["dreaming city","scorn"],"1649087790":["melee"],"1649477996":["ability","super"],"1651323507":[],"1663914658":["solar"],"1663914659":["solar"],"1663914664":["fusion rifle","shotgun"],"1663914665":["bow","crucible","hand cannon"],"1663914666":["multikill"],"1663914667":["power weapon"],"1663914668":["super"],"1663914669":["precision"],"1663914670":["power weapon","rocket launcher"],"1663914671":["auto rifle","pulse rifle","trace rifle"],"1680060432":["multikill"],"1680060433":["super"],"1680060440":["grenade","grenade launcher"],"1680060441":["orbs"],"1680060442":["void"],"1680060443":["solar"],"1680060444":["arc"],"1680060445":["finisher"],"1680060446":[],"1680060447":[],"1683584740":["void"],"1706185766":[],"1721560654":["europa","sidearm"],"1722238432":["crucible","void"],"1725345016":["ability","melee","moon","power weapon"],"1725345017":[],"1725345018":["moon"],"1725345019":["precision"],"1725345020":["moon","void"],"1725345022":["arc"],"1725345023":["solar"],"1730393297":[],"1738079222":[],"1742928699":[],"1759191326":["arc","power weapon"],"1761112788":["arc"],"1763752196":["crucible","orbs"],"1764928973":["power weapon","sword"],"1774447862":["precision"],"1776663988":["bake"],"1776663989":["bake"],"1776663991":[],"1777618773":[],"1791735357":["crucible"],"1794825180":["crucible"],"1807819922":[],"1809377325":["bake"],"1812672687":["cabal","strikes"],"1833039879":["super"],"1840698112":["bake"],"1869653095":["kinetic","kinetic weapon","precision"],"1869722155":["crucible"],"1871412061":["crucible"],"1879172711":["crucible"],"1896550563":["crucible"],"1899370350":["finisher"],"1912981534":[],"1913307766":[],"1921694150":["patrol"],"1921694151":["public event"],"1937694075":["bow","europa"],"1940788333":["taken"],"1946763995":["edz","precision"],"1957909841":["melee","solar"],"1961641728":["cosmodrome","finisher","melee"],"1961641729":["ability","cosmodrome","grenade"],"1961641730":["cosmodrome","super"],"1961641731":["ability","cosmodrome"],"1961641732":["cosmodrome"],"1961641733":["cosmodrome","hive"],"1961641734":["cosmodrome","fallen"],"1961641735":["cosmodrome","precision"],"1961641740":["cosmodrome","power weapon"],"1961641741":["cosmodrome","kinetic","kinetic weapon"],"1964834614":["fusion rifle"],"1981198485":["bake"],"1983539982":["pulse rifle"],"2000398275":["bow"],"2003717903":["hand cannon"],"2004184492":["crucible","energy weapon"],"2057293080":["europa","power weapon","sword"],"2068952036":[],"2103714550":["gambit","void"],"2116702321":["crucible"],"2119144665":["crucible","void"],"2119144666":["crucible","solar","void"],"2119144667":["crucible","solar"],"2133003436":["raid"],"2133176491":["pulse rifle"],"2140947776":[],"2140947777":["solar","super"],"2140947784":["taken"],"2140947785":["taken"],"2140947786":["moon","taken"],"2140947787":["cabal"],"2140947788":["hive"],"2140947789":["fallen"],"2140947790":["shotgun"],"2140947791":["hand cannon"],"2173508794":[],"2192699203":[],"2199659922":["hive","moon"],"2199659923":["dreaming city","taken"],"2199659928":["power weapon"],"2199659929":["grenade"],"2199659930":["kinetic"],"2199659931":["energy weapon"],"2199659932":["cabal"],"2199659933":["fallen"],"2199659934":["melee"],"2199659935":["crucible","super"],"2213620835":["sidearm"],"2231267738":["gambit"],"2231267739":["arc","gambit"],"2231267740":["gambit"],"2231267741":["gambit"],"2231267742":["gambit","solar"],"2231267743":["gambit","void"],"2256480378":["champion"],"2259349108":["gambit"],"2259744478":["bow"],"2267981985":["fusion rifle"],"2271002093":[],"2285406418":["bow"],"2289410285":["edz","power weapon"],"2305954616":["lost sector"],"2305954617":["lost sector"],"2305954618":["lost sector"],"2305954619":["lost sector"],"2328867053":["grenade launcher"],"2338128705":[],"2348066127":["europa","precision"],"2363327331":[],"2367242101":["crucible"],"2373217681":["gambit"],"2373217682":["gambit"],"2373217683":["gambit"],"2376000422":[],"2381486111":["arc","edz"],"2390836807":["arc","europa"],"2391068514":["europa","submachine gun"],"2398816281":["fusion rifle"],"2428565738":["submachine gun"],"2429910598":["dreaming city","grenade"],"2429910599":["dreaming city","melee"],"2429910600":["dreaming city","solar"],"2429910601":["dreaming city","solar"],"2429910602":["dreaming city","precision","pulse rifle"],"2429910603":["dreaming city","multikill","trace rifle"],"2429910604":["dreaming city","fusion rifle","multikill"],"2429910605":["dreaming city","precision"],"2429910606":["dreaming city","multikill","shotgun"],"2429910607":["bow","dreaming city","precision"],"2446688288":["dreaming city","finisher"],"2446688289":["dreaming city","super"],"2446688290":["dreaming city","energy weapon"],"2446688291":["dreaming city","kinetic","kinetic weapon"],"2446688293":["dreaming city","power weapon"],"2451202740":["bake"],"2454138478":["multikill"],"2462005227":["void"],"2467068281":["grenade launcher","multikill"],"2469435739":["super"],"2479868260":["edz","public event"],"2494871935":[],"2497038231":["sidearm"],"2500308040":["edz","sniper rifle"],"2508396988":[],"2508396989":["crucible"],"2564393736":[],"2564393737":[],"2587962933":["nessus","sniper rifle"],"2597966745":["europa","grenade"],"2612593448":["crucible","iron banner"],"2612593449":["crucible","iron banner","solar","void"],"2612593450":["crucible","iron banner","super"],"2612593451":["crucible","iron banner","melee","precision"],"2632823372":["arc","crucible"],"2642052560":[],"2642052561":[],"2642052564":["solar"],"2642052565":["precision","scout rifle","sniper rifle"],"2642052566":["void"],"2642052567":["arc"],"2643903220":[],"2653579669":["grenade"],"2655712924":["gambit"],"2661223204":["patrol"],"2662637005":["public event"],"2663541547":[],"2675137426":["gambit"],"2682789196":["europa","power weapon","rocket launcher"],"2695042788":["void"],"2697214271":["europa","melee"],"2703627837":["hand cannon"],"2719669554":["precision"],"2729271716":["crucible"],"2734163509":["power weapon","solar"],"2755859940":["crucible","solar"],"2757981005":["multikill","super"],"2780182450":["void"],"2781627980":["crucible"],"2805818748":["arc"],"2808722824":["arc","scorn"],"2808722825":["scorn","void"],"2808722826":["scorn"],"2808722827":["finisher"],"2808722828":["ability","super"],"2816193016":["pulse rifle"],"2829326474":["arc","crucible"],"2833790084":[],"2833790085":["moon"],"2833790088":[],"2833790089":["gambit"],"2833790090":["public event"],"2833790091":["europa","patrol"],"2833790092":[],"2833790093":[],"2833790094":["public event"],"2833790095":["europa","patrol"],"2846520475":["hand cannon","precision"],"2849007504":["auto rifle"],"2850552048":["raid"],"2850552049":["arc","raid","solar","void"],"2850552050":["raid"],"2850552051":["raid"],"2850552055":["orbs","raid"],"2850564884":["crucible"],"2856178253":["energy weapon","europa"],"2858316395":[],"2859924064":["kinetic","kinetic weapon"],"2859924065":["energy weapon"],"2859924072":["ability","solar"],"2859924073":["ability","arc"],"2859924074":["ability","arc","solar"],"2859924075":["ability","void"],"2859924076":["grenade"],"2859924077":["melee"],"2859924078":["super"],"2859924079":["finisher"],"2864963410":["crucible","solar"],"2864963411":["crucible"],"2864963412":["crucible"],"2864963413":["crucible","void"],"2864963414":["arc","crucible"],"2864963415":["crucible"],"2876701650":["precision","scout rifle"],"2876701651":["precision"],"2876701656":["multikill","shotgun"],"2876701657":["precision","pulse rifle"],"2876701658":["multikill","submachine gun"],"2876701659":["hand cannon","precision"],"2876701660":["precision","sidearm"],"2876701661":["auto rifle","multikill"],"2876701662":["multikill","power weapon","sword"],"2876701663":["precision","sniper rifle"],"2893357936":["power weapon","rocket launcher","scout rifle","sniper rifle"],"2893357937":["kinetic","kinetic weapon"],"2893357938":["energy weapon"],"2893357939":["power weapon"],"2893357941":["power weapon","shotgun"],"2893357942":["auto rifle","hand cannon","machine gun","moon"],"2893357943":["bow","grenade launcher","pulse rifle"],"2893357948":["hand cannon","multikill","power weapon","shotgun"],"2893357949":["auto rifle","machine gun","multikill","pulse rifle"],"2897490274":["europa","super"],"2903204355":["fallen","strikes"],"2903313662":["edz"],"2909360704":["void"],"2909360705":["solar"],"2909360706":["super"],"2909360707":[],"2909360708":["energy weapon","moon"],"2909360709":["kinetic","kinetic weapon"],"2909360710":["arc"],"2909360711":["nessus","power weapon"],"2909360716":["melee"],"2909360717":["grenade"],"2910256928":[],"2910256929":["power weapon"],"2910887039":["bake"],"2915388915":["europa","sniper rifle"],"2922106190":["europa","hand cannon"],"2930833968":["multikill","pulse rifle"],"2930833969":["multikill"],"2930833970":["hand cannon","multikill"],"2930833971":["multikill","power weapon"],"2930833972":["multikill","sniper rifle"],"2930833973":["multikill","power weapon","rocket launcher"],"2930833974":["multikill","shotgun"],"2930833975":["grenade launcher","multikill"],"2930833978":["solar"],"2932225192":["bake"],"2940269474":["melee"],"2942719529":[],"2943701307":["solar"],"2946797520":["crucible"],"2950606128":["bake"],"2953753033":["gambit"],"2987639079":["sniper rifle"],"2988631849":["bake"],"3038846813":["solar"],"3051422226":[],"3066153609":["bake"],"3070629378":["lost sector"],"3070629379":["ability","super"],"3082636487":["bake"],"3090126239":["sidearm"],"3099386391":["super"],"3106430225":["europa","finisher"],"3109359396":["hand cannon","moon"],"3109359397":["moon","multikill","precision"],"3109359400":["moon","orbs"],"3109359401":["melee","moon"],"3109359402":["moon","submachine gun"],"3109359403":["auto rifle","moon"],"3109359404":["moon","solar"],"3109359405":["arc","moon"],"3109359406":["grenade","moon"],"3109359407":["moon","void"],"3134246761":["sidearm"],"3138772186":["arc"],"3141754354":["bake"],"3141795163":["auto rifle"],"3144456305":["crucible"],"3147705087":["melee"],"3155878395":["melee"],"3167111216":["melee"],"3167111217":["precision"],"3167111224":["fallen"],"3167111225":["hive"],"3167111226":["cabal"],"3167111227":["dreaming city","scorn"],"3167111228":["gambit","taken"],"3167111229":["vex"],"3167111230":["gambit","pulse rifle"],"3167111231":[],"3178157690":["super"],"3181364740":["cosmodrome","patrol"],"3181364741":["cosmodrome","energy weapon"],"3181364743":["cosmodrome"],"3186325460":["public event"],"3186325461":[],"3186325462":["adventure","crucible"],"3186325463":["lost sector"],"3191735197":["gambit"],"3207732940":[],"3209637560":["grenade"],"3214882532":[],"3214882533":[],"3219965079":["scout rifle"],"3238546247":["hand cannon"],"3249939223":["crucible"],"3268553440":["gambit"],"3268553441":["finisher"],"3268553448":["crucible"],"3268553449":[],"3268553450":[],"3268553451":["moon"],"3268553452":["strike"],"3268553453":["moon"],"3268553454":[],"3268553455":[],"3285890782":["crucible"],"3286744862":["crucible","melee"],"3305117363":["arc","gambit"],"3312152065":["super"],"3337739523":[],"3346345957":["crucible"],"3357287242":[],"3361783295":["crucible"],"3386849259":["gambit"],"3401935316":["europa","power weapon"],"3408756889":["edz","multikill","super"],"3408852116":["gambit","melee","solar"],"3408852117":["gambit","precision","solar","void"],"3408852118":["gambit","super","void"],"3414352434":["crucible"],"3438972653":["power weapon","rocket launcher"],"3442628158":["crucible"],"3449625264":["auto rifle","machine gun","pulse rifle","submachine gun"],"3449625265":["vex"],"3449625266":[],"3449625267":["grenade launcher","power weapon","rocket launcher"],"3449625268":["multikill"],"3449625269":["orbs"],"3449625270":["cabal"],"3449625271":["multikill","vex"],"3449625276":["lost sector"],"3449625277":["public event"],"3481851003":["gambit"],"3486486983":["europa","void"],"3497386880":[],"3512622966":["grenade"],"3514703992":["melee"],"3522328430":["finisher"],"3522663041":["void"],"3522663042":["solar"],"3522663043":["arc","melee"],"3525239115":["crucible","super"],"3531980021":["dreaming city","scorn"],"3535952788":["crucible","void"],"3539440752":["multikill"],"3539440753":["champion","champions"],"3539440754":["kinetic","kinetic weapon"],"3539440755":[],"3539440756":["power weapon"],"3539440757":["energy weapon"],"3539440758":["power weapon","rocket launcher"],"3539440759":["sniper rifle"],"3539440766":["multikill"],"3540140705":["lost sector"],"3540140708":["moon","public event"],"3540140709":["moon","patrol"],"3540140710":["moon"],"3540140711":[],"3541627175":["crucible"],"3560267478":["melee"],"3597986944":["hive","moon"],"3597986945":["fallen","finisher","moon"],"3597986946":["hive","moon"],"3597986947":["fallen","moon"],"3597986949":["finisher","moon","vex"],"3597986950":["finisher","hive","moon"],"3597986951":["fallen","moon"],"3606312404":["crucible","solar"],"3628771136":["pulse rifle","scout rifle"],"3628771137":["shotgun"],"3628771138":["sniper rifle"],"3628771139":["melee","power weapon"],"3628771140":["energy weapon"],"3628771141":["power weapon"],"3628771142":["multikill"],"3628771143":["auto rifle","submachine gun"],"3628771148":["hand cannon"],"3628771149":["edz","precision"],"3636568846":["pulse rifle"],"3636655077":[],"3645548848":["fallen"],"3645548849":["taken"],"3645548850":["hive"],"3645548852":[],"3645548853":[],"3645548854":[],"3645548855":[],"3645548862":["kinetic","kinetic weapon"],"3647168216":["grenade"],"3664752320":["power weapon","void"],"3671936696":["grenade"],"3675595381":["crucible"],"3679104028":["solar","super"],"3679104030":[],"3679104031":["arc","void"],"3683313874":["void"],"3693294824":["crucible","grenade"],"3696295486":["sidearm"],"3697234118":["scout rifle"],"3713071908":["ability","crucible"],"3721656876":["sniper rifle"],"3723696828":["multikill","shotgun"],"3731062163":["strikes","taken"],"3738574300":["bake","forest"],"3782095609":["crucible","super"],"3795659409":["machine gun"],"3831027416":["europa","lost sector","power weapon","sword"],"3831027417":["fusion rifle","lost sector"],"3831027418":["lost sector","power weapon","rocket launcher"],"3831027419":["europa","grenade launcher","lost sector"],"3831027422":["lost sector","precision"],"3831027423":["lost sector","moon","trace rifle"],"3846232056":["taken"],"3846232057":[],"3846232058":[],"3846232059":["power weapon"],"3846956448":["power weapon"],"3846956449":["hand cannon","multikill","power weapon","shotgun"],"3846956450":["kinetic","kinetic weapon"],"3846956451":["energy weapon"],"3846956452":["bow","grenade launcher","pulse rifle"],"3846956453":["power weapon","rocket launcher","scout rifle","sniper rifle"],"3846956454":["power weapon","shotgun","submachine gun"],"3846956455":["auto rifle","hand cannon","machine gun"],"3846956462":["auto rifle","machine gun","multikill","pulse rifle","submachine gun"],"3846956463":["bow","grenade launcher","multikill","power weapon","rocket launcher"],"3854280025":[],"3896716771":["auto rifle","europa"],"3899430886":["crucible"],"3904432054":["europa","fusion rifle"],"3909982964":["lost sector","nessus"],"3917716859":["precision","submachine gun"],"3919389444":["precision","solar","strike","super"],"3919389445":["crucible","iron banner","multikill","solar","strike","strikes","void"],"3919389446":["crucible","finisher","iron banner","melee","strike","strikes","void"],"3921551053":["nessus","super"],"3954920295":["edz","fallen"],"3958224565":["nessus"],"3971836963":["strikes","vex"],"3990791875":["solar"],"3993430445":["lost sector","nessus"],"3993430447":["lost sector"],"4004837762":["crucible","precision"],"4010546641":["crucible"],"4019596374":["nightfall"],"4019596375":["crimson days","crucible"],"4037933170":["crucible"],"4042851399":["crucible"],"4044330008":["europa"],"4044330009":[],"4044330010":["moon"],"4044330011":["public event"],"4044330013":["champion"],"4044330015":["dreaming city"],"4050047257":[],"4050047258":[],"4050047259":["void"],"4050047260":["arc"],"4050047261":["solar"],"4050047262":["precision","scout rifle","sniper rifle"],"4050047263":["bow","grenade launcher","multikill","power weapon","rocket launcher"],"4059065847":["super"],"4060319896":["nessus"],"4084493733":["machine gun"],"4086613787":["crucible","void"],"4095766153":["dreaming city"],"4097373632":[],"4097373633":["gambit","submachine gun"],"4097373634":["crucible","power weapon","sword"],"4097373635":["gambit","sidearm"],"4097373637":["gambit","pulse rifle"],"4097373638":["bow"],"4097373639":["scout rifle"],"4108896452":["edz","precision"],"4114666828":["solar"],"4122700291":["edz","void"],"4126111451":["grenade launcher"],"4145233940":["europa","grenade launcher"],"4153081286":["cabal","edz"],"4187422269":[],"4197398846":["crucible"],"4203745889":["bake"],"4209915572":["bow"],"4235693605":["arc"],"4237572676":["nessus","orbs"],"4240324233":["multikill","power weapon","sword"],"4243637120":["crucible"],"4247773596":["auto rifle","precision"],"4249475965":["gambit"],"4251951858":["crimson days","crucible"],"4251951859":["crimson days","crucible"],"4251951860":["crucible"],"4251951862":["crucible"],"4251951863":["crucible"],"4256487838":["bake"],"4259131291":["ability","solar"],"4269063328":["finisher"],"4269063329":["ability","super"],"4269063330":["vex","void"],"4269063331":["vex"],"4275087105":["bake"]}